pynlog/__init__.py
pynlog/_consolewriter.py
pynlog/_filewriter.py
pynlog/_formatter.py
pynlog/_level.py
pynlog/_log.py
pynlog/_logentry.py
pynlog/_utility.py
pynlog/_writer.py
pynlog/py.typed
pynlog-0.1.0.dist-info/METADATA
pynlog-0.1.0.dist-info/WHEEL
pynlog-0.1.0.dist-info/licenses/LICENSE
pynlog-0.1.0.dist-info/RECORD
