Metadata-Version: 2.4
Name: pynlog
Version: 0.1.0
Summary: A simple logger that prints logs to the console and to a file out of the box.
Project-URL: Homepage, https://github.com/m-j-z/pynlog
Project-URL: Issues, https://github.com/m-j-z/pynlog/issues
Author-email: Michael <michaelzdv7@gmail.com>
License-Expression: MIT
License-File: LICENSE
Requires-Python: >=3.9
